uselesscapitalquiz/Capital_Quiz.py
uselesscapitalquiz/__init__.py
uselesscapitalquiz/all_mode.py
uselesscapitalquiz/easy_mode.py
uselesscapitalquiz/hard_mode.py
uselesscapitalquiz/lists.py
uselesscapitalquiz/moderate_mode.py
uselesscapitalquiz/new.py
uselesscapitalquiz/test.py
uselesscapitalquiz-3.14159265358979323846264338327950288419716939937510582097494459230781640628620899862803482534211706798214808651328230664709384460955058223172535940812848111745028410270193852110555964462294895493038196442881097566593.dist-info/METADATA
uselesscapitalquiz-3.14159265358979323846264338327950288419716939937510582097494459230781640628620899862803482534211706798214808651328230664709384460955058223172535940812848111745028410270193852110555964462294895493038196442881097566593.dist-info/WHEEL
uselesscapitalquiz-3.14159265358979323846264338327950288419716939937510582097494459230781640628620899862803482534211706798214808651328230664709384460955058223172535940812848111745028410270193852110555964462294895493038196442881097566593.dist-info/top_level.txt
uselesscapitalquiz-3.14159265358979323846264338327950288419716939937510582097494459230781640628620899862803482534211706798214808651328230664709384460955058223172535940812848111745028410270193852110555964462294895493038196442881097566593.dist-info/RECORD
